lemai_sdk/__init__.py
lemai_sdk/client.py
lemai_sdk/exceptions.py
lemai_sdk/providers/__init__.py
lemai_sdk/providers/base.py
lemai_sdk/providers/config.py
lemai_sdk/providers/custom.py
lemai_sdk/providers/gemini.py
lemai_sdk/providers/openai.py
lemai_sdk-0.1.2.dist-info/licenses/LICENSE
lemai_sdk-0.1.2.dist-info/METADATA
lemai_sdk-0.1.2.dist-info/WHEEL
lemai_sdk-0.1.2.dist-info/top_level.txt
lemai_sdk-0.1.2.dist-info/RECORD
