Metadata-Version: 2.4
Name: lemai-sdk
Version: 0.1.2
Summary: Multi-provider AI chat SDK (OpenAI, Gemini, Custom)
Author: Erick Lema
License: MIT
Requires-Python: >=3.7
License-File: LICENSE
Requires-Dist: openai>=1.0.0
Requires-Dist: requests>=2.28.0
Requires-Dist: python-dotenv>=1.0.0
Dynamic: author
Dynamic: description
Dynamic: description-content-type
Dynamic: license
Dynamic: license-file
Dynamic: requires-dist
Dynamic: requires-python
Dynamic: summary
